[
  {
    "user2": [
      {
        "date": "05/23/2025",
        "entry_time": "13:00",
        "exit_time": "16:00"
      },
      {
        "date": "05/24/2025",
        "entry_time": "13:13",
        "exit_time": "17:55"
      },
      {
        "date": "05/24/2025",
        "entry_time": "17:55",
        "exit_time": "18:03"
      },
      {
        "date": "05/24/2025",
        "entry_time": "18:04",
        "exit_time": "18:04"
      },
      {
        "date": "05/24/2025",
        "entry_time": "18:12",
        "exit_time": "18:13"
      }
    ]
  },
  {
    "user1": [
      {
        "date": "05/24/2025",
        "entry_time": "18:24",
        "exit_time": "18:27"
      },
      {
        "date": "05/24/2025",
        "entry_time": "18:28",
        "exit_time": "18:28"
      }
    ]
  }
]